courseraoauth2client/__init__.py
courseraoauth2client/main.py
courseraoauth2client/oauth2.py
courseraoauth2client/utils.py
courseraoauth2client/commands/__init__.py
courseraoauth2client/commands/config.py
courseraoauth2client/commands/version.py
courseraoauth2client-0.0.1.dist-info/DESCRIPTION.rst
courseraoauth2client-0.0.1.dist-info/entry_points.txt
courseraoauth2client-0.0.1.dist-info/METADATA
courseraoauth2client-0.0.1.dist-info/metadata.json
courseraoauth2client-0.0.1.dist-info/RECORD
courseraoauth2client-0.0.1.dist-info/top_level.txt
courseraoauth2client-0.0.1.dist-info/WHEEL
