Metadata-Version: 1.1
Name: courseraoauth2client
Version: 0.0.1
Summary: An OAuth2 client for the Coursera App Platform.
Home-page: https://github.com/coursera/courseraoauth2client
Author: Chris Liu
Author-email: cliu@coursera.org
License: Apache
Keywords: coursera sdk cli tool oauth2
Platform: UNKNOWN
Classifier: Development Status :: 5 - Production/Stable
Classifier: License :: OSI Approved :: Apache Software License
Classifier: Programming Language :: Python :: 2.7
